main.py
vigyan-0.0.1.dist-info/licenses/LICENSE
vigyan-0.0.1.dist-info/METADATA
vigyan-0.0.1.dist-info/WHEEL
vigyan-0.0.1.dist-info/top_level.txt
vigyan-0.0.1.dist-info/RECORD
