Metadata-Version: 2.4
Name: vigyan
Version: 0.0.1
Summary: High accuracy agentic search on scientific documents with citations
Requires-Python: >=3.12
License-File: LICENSE
Dynamic: license-file
